flyvec/__init__.py
flyvec/_nbdev.py
flyvec/core.py
flyvec/downloader.py
flyvec/flyvec_train.py
flyvec/path_fixes.py
flyvec/tokenizer.py
flyvec/train_flyvec.py
flyvec/utils.py
flyvec/src/acc_cuda.cu
flyvec/src/cu_special_reduction.cu
flyvec/src/cuda_funcs.cu
flyvec/src/cuda_helpers.cu
flyvec/src/memory_allocator.h
flyvec/src/model_arrays.cu
flyvec/src/model_arrays.h
flyvec/src/model_descriptor.cu
flyvec/src/model_descriptor.h
flyvec/src/prune_input.cpp
flyvec/src/remove_words.cpp
flyvec/src/short_make
flyvec/src/test_inv.cpp
flyvec/src/test_preprocess.cpp
flyvec-0.3.2.dist-info/LICENSE
flyvec-0.3.2.dist-info/METADATA
flyvec-0.3.2.dist-info/WHEEL
flyvec-0.3.2.dist-info/entry_points.txt
flyvec-0.3.2.dist-info/top_level.txt
flyvec-0.3.2.dist-info/RECORD
