Metadata-Version: 2.1
Name: flyvec
Version: 0.3.2
Summary: A biologically inspired method to create sparse, binary word vectors
Home-page: https://github.com/bhoov/flyvec/tree/master/
Author: "Benjamin Hoover <benhoover34@gmail.com>, Dima Krotov <krotov@ibm.com>"
Author-email: "benhoover34@gmail.com"
License: Apache Software License 2.0
Keywords: GloVE Word2Vec Wordvector NLP Bioinspired AI ML sparse binary
Platform: UNKNOWN
Classifier: Development Status :: 5 - Production/Stable
Classifier: Intended Audience :: Developers
Classifier: License :: OSI Approved :: Apache Software License
Classifier: Natural Language :: English
Classifier: Programming Language :: Python :: 3.6
Classifier: Programming Language :: Python :: 3.7
Classifier: Programming Language :: Python :: 3.8
Requires-Python: >=3.6
Requires-Dist: numpy (>=1.5.0)
Requires-Dist: gensim
Requires-Dist: regex
Requires-Dist: boto3
Requires-Dist: cached-property
Requires-Dist: progressbar
Requires-Dist: fastcore
Requires-Dist: pyyaml
